{
  "project_info": {
    "project_number": "899864541024",
    "project_id": "scalendar-a8277",
    "storage_bucket": "scalendar-a8277.firebasestorage.app"
  },
  "client": [
    {
      "client_info": {
        "mobilesdk_app_id": "1:899864541024:android:e6aca802b766372321d005",
        "android_client_info": {
          "package_name": "com.example.ai"
        }
      },
      "oauth_client": [
        {
          "client_id": "899864541024-0jbf5likn8cs85argo2d2ujihrsrujnb.apps.googleusercontent.com",
          "client_type": 1,
          "android_info": {
            "package_name": "com.example.ai",
            "certificate_hash": "838e021fca5ab8c3fe3e9c886940db2a5d70fb08"
          }
        },
        {
          "client_id": "899864541024-778o03pdr0r5t7jog5ekeg56niqvdcf2.apps.googleusercontent.com",
          "client_type": 1,
          "android_info": {
            "package_name": "com.example.ai",
            "certificate_hash": "a690554cfa60c237b2cda38af131b641d02ccad8"
          }
        },
        {
          "client_id": "899864541024-kdokciud33jc3ivqn2mdthji3u3tre24.apps.googleusercontent.com",
          "client_type": 1,
          "android_info": {
            "package_name": "com.example.ai",
            "certificate_hash": "8550841f9e00d62c463e4370c0ed2eaa47c5bf3a"
          }
        },
        {
          "client_id": "899864541024-mmfpf0ffvjrljh054888htrmo1ti7rus.apps.googleusercontent.com",
          "client_type": 1,
          "android_info": {
            "package_name": "com.example.ai",
            "certificate_hash": "b16e6bdf4f4000a7153374532ee6a64101bf5a88"
          }
        },
        {
          "client_id": "899864541024-ta45utss8824jdrmfvanp0ruglcc9qtm.apps.googleusercontent.com",
          "client_type": 3
        }
      ],
      "api_key": [
        {
          "current_key": "AIzaSyDwzdJXQxv9r0c8MKlu7JR9RBmAA06Pr-g"
        }
      ],
      "services": {
        "appinvite_service": {
          "other_platform_oauth_client": [
            {
              "client_id": "899864541024-ta45utss8824jdrmfvanp0ruglcc9qtm.apps.googleusercontent.com",
              "client_type": 3
            }
          ]
        }
      }
    }
  ],
  "configuration_version": "1"
}